MANIFEST.in
README.rst
setup.py
collective/__init__.py
collective/__init__.pyc
collective.geo.opensearch.egg-info/PKG-INFO
collective.geo.opensearch.egg-info/SOURCES.txt
collective.geo.opensearch.egg-info/dependency_links.txt
collective.geo.opensearch.egg-info/entry_points.txt
collective.geo.opensearch.egg-info/namespace_packages.txt
collective.geo.opensearch.egg-info/not-zip-safe
collective.geo.opensearch.egg-info/requires.txt
collective.geo.opensearch.egg-info/top_level.txt
collective/geo/__init__.py
collective/geo/__init__.pyc
collective/geo/opensearch/__init__.py
collective/geo/opensearch/__init__.pyc
collective/geo/opensearch/configure.zcml
collective/geo/opensearch/interfaces.py
collective/geo/opensearch/interfaces.pyc
collective/geo/opensearch/tests.py
collective/geo/opensearch/version.txt
collective/geo/opensearch/browser/__init__.py
collective/geo/opensearch/browser/__init__.pyc
collective/geo/opensearch/browser/atomview.pt
collective/geo/opensearch/browser/atomview.py
collective/geo/opensearch/browser/atomview.pyc
collective/geo/opensearch/browser/configure.zcml
collective/geo/opensearch/browser/envelope.pt
collective/geo/opensearch/browser/extkmlview.pt
collective/geo/opensearch/browser/extkmlview.py
collective/geo/opensearch/browser/extkmlview.pyc
collective/geo/opensearch/browser/folderview.pt
collective/geo/opensearch/browser/folderview.py
collective/geo/opensearch/browser/folderview.pyc
collective/geo/opensearch/browser/kmlview.pt
collective/geo/opensearch/browser/kmlview.py
collective/geo/opensearch/browser/kmlview.pyc
collective/geo/opensearch/browser/linestring.pt
collective/geo/opensearch/browser/maplayers.py
collective/geo/opensearch/browser/maplayers.pyc
collective/geo/opensearch/browser/mapview.pt
collective/geo/opensearch/browser/mapview.py
collective/geo/opensearch/browser/mapview.pyc
collective/geo/opensearch/browser/point.pt
collective/geo/opensearch/browser/polygon.pt
collective/geo/opensearch/browser/rssview.pt
collective/geo/opensearch/browser/rssview.py
collective/geo/opensearch/browser/rssview.pyc
collective/geo/opensearch/browser/utils.py
collective/geo/opensearch/browser/utils.pyc
collective/geo/opensearch/locales/collective.geo.opensearch.pot
collective/geo/opensearch/locales/rebuild.sh
collective/geo/opensearch/locales/es/LC_MESSAGES/collective.geo.opensearch.mo
